Workbook

Sheet 02_サマリー_요약
A1: 3ヶ月 必要経費 サマリー ／ 3개월 필요경비 요약
A2: A＝運営経費のみ／B＝A＋通関費／C＝B＋商品仕入。用途に応じて使い分けてください。／ 용도에 따라 구분해 사용하세요.
A4: 運営経費（3ヶ月）／ 운영경비(3개월)
B5: 区分 구분 | C5: 月額(W) 월액(W) | D5: 3ヶ月(W) 3개월(W) | E5: 3ヶ月(円) 3개월(엔) | F5: メモ 메모
A6: 1 | B6: ① 固定費 고정비 | C6: ='01_明細_명세'!C10 -> 2825000 | D6: ='01_明細_명세'!D10 -> 8475000 | E6: ='01_明細_명세'!E10 -> 932250 | F6: 給与・家賃・管理費・税理士 ／ 급여·임대료·관리비·세무사
A7: 2 | B7: ② 広告費 광고비 | C7: ='01_明細_명세'!C14 -> 3960000 | D7: ='01_明細_명세'!D14 -> 11880000 | E7: ='01_明細_명세'!E14 -> 1306800 | F7: メタ広告（7/18-8/19実績）／ 메타 광고
A8: 3 | B8: ③ 変動費 변동비 | C8: ='01_明細_명세'!C26 -> 710460 | D8: ='01_明細_명세'!D26 -> 2131380 | E8: ='01_明細_명세'!E26 -> 234451.8 | F8: 実績平均から算出 ／ 실적 평균
A9: 4 | B9: ④ 外注費 외주비 | C9: ='01_明細_명세'!C30 -> 500000 | D9: ='01_明細_명세'!D30 -> 1500000 | E9: ='01_明細_명세'!E30 -> 165000 | F9: ★実額未提示 ／ ★실액 미제출
A10: A | B10: 運営経費 3ヶ月 合計 운영경비 3개월 합계 | C10: =SUM(C6:C9) -> 7995460 | D10: =SUM(D6:D9) -> 23986380 | E10: =SUM(E6:E9) -> 2638501.8
A12: 通関費 ／ 통관비
B13: 区分 구분 | D13: 金額(W) 금액(W) | E13: 金額(円) 금액(엔) | F13: メモ 메모
B14: 33個分 通関費（支払済） 33개분 통관비(지급완료) | D14: =1045911 -> 1045911 | E14: =D14*'00_前提_전제'!$B$5 -> 115050.21 | F14: 9/10 LJ関税事務所 I26-100263M・検算済み ／ 검산 완료
B15: 800個分 通関費（見積） 800개분 통관비(견적) | D15: ='00_前提_전제'!$B$8*'00_前提_전제'!$B$7/'00_前提_전제'!$B$5 -> 7272727.3 | E15: =D15*'00_前提_전제'!$B$5 -> 800000 | F15: ★通関士見積が未提示。1,000円/個で仮置き ／ ★견적 미제출
A16: B | B16: A ＋ 通関費 A + 통관비 | D16: =D10+SUM(D14:D15) -> 32305018 | E16: =D16*'00_前提_전제'!$B$5 -> 3553552
A18: 商品仕入 ／ 상품 매입
B19: 800個 仕入原価 800개 매입원가 | D19: ='00_前提_전제'!$B$9*'00_前提_전제'!$B$7 -> 112000000 | E19: =D19*'00_前提_전제'!$B$5 -> 12320000 | F19: 仮ミックス S40:M40:L20（S10万/M15万/L20万W）／ 가정 믹스
A20: C | B20: 総所要資金（B ＋ 仕入） 총 소요자금(B + 매입) | D20: =D16+D19 -> 1.4430502e+08 | E20: =D20*'00_前提_전제'!$B$5 -> 15873552
A22: 過去実績との比較 ／ 과거 실적과 비교
B23: 項目 항목 | D23: 金額(W) 금액(W) | E23: 金額(円) 금액(엔) | F23: メモ 메모
B24: 今回の運営経費 月額 이번 운영경비 월액 | D24: =D10/'00_前提_전제'!$B$6 -> 7995460 | E24: =D24*'00_前提_전제'!$B$5 -> 879500.6
B25: 過去9ヶ月の月平均 과거 9개월 월평균 | D25: =37875450/9 -> 4208383.3 | E25: =D25*'00_前提_전제'!$B$5 -> 462922.17 | F25: 2025.12-2026.08 総支出37,875,450÷9 ／ 총지출÷9
B26: 倍率 배율 | D26: =D24/D25 -> 1.8998887 | F26: ★主因はメタ広告 396万W/月（過去は約13万W/月）／ ★주요인은 메타 광고
A27: 注記
A28: A＝毎月必ず出ていく運営経費。B＝それに通関費を足した額。C＝商品仕入まで含めた総所要資金。
A29: A＝매월 반드시 나가는 운영경비. B＝거기에 통관비를 더한 금액. C＝상품 매입까지 포함한 총 소요자금.
A30: ★800個の通関費（通関士見積）と外注費の実額が入れば、B と C が確定します。
A31: ★800개 통관비(통관사 견적)와 외주비 실액이 들어오면 B와 C가 확정됩니다.

Sheet 03_月別_월별
A1: 月別の資金繰り ／ 월별 자금 흐름
A2: 運営経費は毎月同額。通関費と仕入は発生月に計上しています。／ 운영경비는 매월 동일. 통관비와 매입은 발생월에 계상.
A4: 項目 항목 | B4: 2026-10 2026-10 | C4: 2026-11 2026-11 | D4: 2026-12 2026-12 | E4: 3ヶ月計 3개월 계 | F4: メモ 메모
A5: ① 固定費 고정비 | B5: ='01_明細_명세'!C10 -> 2825000 | C5: ='01_明細_명세'!C10 -> 2825000 | D5: ='01_明細_명세'!C10 -> 2825000 | E5: =SUM(B5:D5) -> 8475000 | F5: 給与200万＋家賃55万＋管理16.5万＋税理士11万 ／ 급여200만+임대료55만+관리16.5만+세무사11만
A6: ② 広告費 광고비 | B6: ='01_明細_명세'!C14 -> 3960000 | C6: ='01_明細_명세'!C14 -> 3960000 | D6: ='01_明細_명세'!C14 -> 3960000 | E6: =SUM(B6:D6) -> 11880000 | F6: メタ広告 ／ 메타 광고
A7: ③ 変動費 변동비 | B7: ='01_明細_명세'!C26 -> 710460 | C7: ='01_明細_명세'!C26 -> 710460 | D7: ='01_明細_명세'!C26 -> 710460 | E7: =SUM(B7:D7) -> 2131380 | F7: 実績平均 ／ 실적 평균
A8: ④ 外注費 외주비 | B8: ='01_明細_명세'!C30 -> 500000 | C8: ='01_明細_명세'!C30 -> 500000 | D8: ='01_明細_명세'!C30 -> 500000 | E8: =SUM(B8:D8) -> 1500000 | F8: ★実額未提示 ／ ★실액 미제출
A9: A 運営経費 小計 A 운영경비 소계 | B9: =SUM(B5:B8) -> 7995460 | C9: =SUM(C5:C8) -> 7995460 | D9: =SUM(D5:D8) -> 7995460 | E9: =SUM(B9:D9) -> 23986380 | F9: 毎月同額 ／ 매월 동일
A10: 通関費 33個分 통관비 33개분 | B10: =0 -> 0 | C10: =1045911 -> 1045911 | D10: =0 -> 0 | E10: =SUM(B10:D10) -> 1045911 | F10: 9/10 支払済（立替）／ 9/10 지급완료(대납)
A11: 通関費 800個分 통관비 800개분 | B11: =0 -> 0 | C11: ='00_前提_전제'!$B$8*'00_前提_전제'!$B$7/'00_前提_전제'!$B$5 -> 7272727.3 | D11: =0 -> 0 | E11: =SUM(B11:D11) -> 7272727.3 | F11: ★11月中旬入荷想定 ／ ★11월 중순 입고 가정
A12: 800個 仕入原価 800개 매입원가 | B12: ='00_前提_전제'!$B$9*'00_前提_전제'!$B$7*0.3 -> 33600000 | C12: ='00_前提_전제'!$B$9*'00_前提_전제'!$B$7*0.7 -> 78400000 | D12: =0 -> 0 | E12: =SUM(B12:D12) -> 112000000 | F12: 前金30%／残金70%（仮）／ 선금30%/잔금70%(가정)
A13: C 月別 所要資金 C 월별 소요자금 | B13: =B9+B10+B11+B12 -> 41595460 | C13: =C9+C10+C11+C12 -> 94714098 | D13: =D9+D10+D11+D12 -> 7995460 | E13: =SUM(B13:D13) -> 1.4430502e+08 | F13: この月に必要な現金 ／ 이 달에 필요한 현금
A15: 円換算（C 行） 엔 환산(C 행) | B15: =A13*'00_前提_전제'!$B$5 -> 4575500.6 | C15: =B13*'00_前提_전제'!$B$5 -> 10418551 | D15: =C13*'00_前提_전제'!$B$5 -> 879500.6 | E15: =E13*'00_前提_전제'!$B$5 -> 15873552
A17: 注記
A18: ★11月に資金の山が来ます。通関費と仕入残金が同じ月に重なるためです。
A19: ★11월에 자금 피크가 옵니다. 통관비와 매입 잔금이 같은 달에 겹치기 때문입니다.
A20: 前金30%/残金70%とリードタイムは仮置きです。実際の契約条件に置き換えてください。
A21: 선금30%/잔금70%와 리드타임은 가정치입니다. 실제 계약 조건으로 교체해 주세요.

Sheet 01_明細_명세
A1: 3ヶ月 必要経費 明細 ／ 3개월 필요경비 명세
A2: 月額×月数で算出。★は実額が未提示のため仮置きです。／ 월액×개월수로 산출. ★는 실액 미제출로 가정치입니다.
A4: 区分 구분 | B4: 項目 항목 | C4: 月額(W) 월액(W) | D4: 3ヶ月(W) 3개월(W) | E4: 3ヶ月(円) 3개월(엔) | F4: 確度 확도 | G4: 根拠 근거
A5: ① 固定費 ／ 고정비
B6: 給与 급여 | C6: 2000000 | D6: =C6*'00_前提_전제'!$B$6 -> 6000000 | E6: =D6*'00_前提_전제'!$B$5 -> 660000 | F6: 実績 | G6: 今後の予想費用 E9（直近の月額支出基準）／ 향후 예상비용 E9
B7: 家賃 임대료 | C7: 550000 | D7: =C7*'00_前提_전제'!$B$6 -> 1650000 | E7: =D7*'00_前提_전제'!$B$5 -> 181500 | F7: 実績 | G7: 同 E7 ／ 동 E7
B8: 管理費 관리비 | C8: 165000 | D8: =C8*'00_前提_전제'!$B$6 -> 495000 | E8: =D8*'00_前提_전제'!$B$5 -> 54450 | F8: 実績 | G8: 同 E10 ／ 동 E10
B9: 税理士費用 세무사 비용 | C9: 110000 | D9: =C9*'00_前提_전제'!$B$6 -> 330000 | E9: =D9*'00_前提_전제'!$B$5 -> 36300 | F9: 実績 | G9: 同 E8 ／ 동 E8
B10: ① 固定費 小計 소계 | C10: =SUM(C6:C9) -> 2825000 | D10: =SUM(D6:D9) -> 8475000 | E10: =SUM(E6:E9) -> 932250
A12: ② 広告費 ／ 광고비
B13: メタ広告 메타 광고 | C13: 3960000 | D13: =C13*'00_前提_전제'!$B$6 -> 11880000 | E13: =D13*'00_前提_전제'!$B$5 -> 1306800 | F13: 実績 | G13: 7/18-8/19 実績・付加価値税込 ／ 7/18-8/19 실적·부가세 포함
B14: ② 広告費 小計 소계 | C14: =SUM(C13:C13) -> 3960000 | D14: =SUM(D13:D13) -> 11880000 | E14: =SUM(E13:E13) -> 1306800
A16: ③ 変動費（実績平均）／ 변동비(실적 평균)
B17: 交通費 교통비 | C17: 256667 | D17: =C17*'00_前提_전제'!$B$6 -> 770001 | E17: =D17*'00_前提_전제'!$B$5 -> 84700.11 | F17: 実績 | G17: 実績770,000÷3回 ／ 실적 770,000÷3회
B18: 宅配費 택배비 | C18: 60043 | D18: =C18*'00_前提_전제'!$B$6 -> 180129 | E18: =D18*'00_前提_전제'!$B$5 -> 19814.19 | F18: 実績 | G18: 実績420,300÷7回 ／ 실적 420,300÷7회
B19: EMS EMS | C19: 172100 | D19: =C19*'00_前提_전제'!$B$6 -> 516300 | E19: =D19*'00_前提_전제'!$B$5 -> 56793 | F19: 実績 | G19: 実績688,400÷4回 ／ 실적 688,400÷4회
B20: レビュー・プロモーション 리뷰·프로모션 | C20: 60000 | D20: =C20*'00_前提_전제'!$B$6 -> 180000 | E20: =D20*'00_前提_전제'!$B$5 -> 19800 | F20: 仮 | G20: ★フォトレビュー実績60,000。送料→手数料→入金までの実額は要確認 ／ ★실액 확인 필요
B21: 業務用携帯電話 업무용 휴대폰 | C21: 55500 | D21: =C21*'00_前提_전제'!$B$6 -> 166500 | E21: =D21*'00_前提_전제'!$B$5 -> 18315 | F21: 実績 | G21: 実績55,500 ／ 실적 55,500
B22: 駐車料金 주차요금 | C22: 25550 | D22: =C22*'00_前提_전제'!$B$6 -> 76650 | E22: =D22*'00_前提_전제'!$B$5 -> 8431.5 | F22: 実績 | G22: 実績51,100÷2回 ／ 실적 51,100÷2회
B23: ソフトウェア 소프트웨어 | C23: 9900 | D23: =C23*'00_前提_전제'!$B$6 -> 29700 | E23: =D23*'00_前提_전제'!$B$5 -> 3267 | F23: 実績 | G23: Canva等 実績29,700÷3回 ／ 실적 29,700÷3회
B24: Instagram・その他 인스타그램·기타 | C24: 21700 | D24: =C24*'00_前提_전제'!$B$6 -> 65100 | E24: =D24*'00_前提_전제'!$B$5 -> 7161 | F24: 実績 | G24: 実績108,500÷5回 ／ 실적 108,500÷5회
B25: その他運営費 기타 운영비 | C25: 49000 | D25: =C25*'00_前提_전제'!$B$6 -> 147000 | E25: =D25*'00_前提_전제'!$B$5 -> 16170 | F25: 実績 | G25: 実績98,000÷2回 ／ 실적 98,000÷2회
B26: ③ 変動費（実績平均） 小計 소계 | C26: =SUM(C17:C25) -> 710460 | D26: =SUM(D17:D25) -> 2131380 | E26: =SUM(E17:E25) -> 234451.8
A28: ④ 外注費 ／ 외주비
B29: 外注費 외주비 | C29: 500000 | D29: =C29*'00_前提_전제'!$B$6 -> 1500000 | E29: =D29*'00_前提_전제'!$B$5 -> 165000 | F29: 仮 | G29: ★未提示。LP外注550,000・商品ページ外注200,000の実績から月割 ／ ★미제출
B30: ④ 外注費 小計 소계 | C30: =SUM(C29:C29) -> 500000 | D30: =SUM(D29:D29) -> 1500000 | E30: =SUM(E29:E29) -> 165000

Sheet 04_要確認_확인필요
A1: 要確認リスト ／ 확인 필요 리스트
A2: この3項目が埋まれば金額が確定します。／ 이 3개 항목이 채워지면 금액이 확정됩니다.
A4: # | B4: 項目 항목 | C4: 現在の仮値 현재 가정치 | D4: 影響 영향 | E4: どこで確認できるか 어디서 확인 | F4: メモ 메모
A5: 1 | B5: 800個の通関費 800개 통관비 | C5: 1,000円/個（80万円） | D5: 大 | E5: 通関士から出た800個の見積 ／ 통관사 800개 견적 | F5: 33個便の実績は2,919円/個。800個なら下がる想定で1,000円と置いています ／ 33개 실적 2,919엔/개
A6: 2 | B6: 外注費（月額） 외주비(월액) | C6: 500,000W（3ヶ月150万W） | D6: 中 | E6: 外注先の請求書・見積 ／ 외주처 청구서·견적 | F6: LP外注550,000・商品ページ外注200,000の実績から月割 ／ 실적에서 월할
A7: 3 | B7: レビュー費用の実額 리뷰 비용 실액 | C7: 60,000W/月 | D7: 小 | E7: レビュー施策の実績（送料→手数料→入金まで）／ 리뷰 실적 | F7: フォトレビュー60,000の1回実績のみ。送料・手数料・入金サイトまで含めた実額をご提示ください ／ 실액 제시 바랍니다
A8: 4 | B8: 800個のSKU内訳 800개 SKU 내역 | C8: S40:M40:L20 仮 | D8: 中 | E8: 発注書・PI ／ 발주서·PI | F8: 平均仕入原価140,000Wはこの比率での加重平均 ／ 평균 매입원가는 이 비율의 가중평균
A9: 5 | B9: 入荷月・支払条件 입고월·지급조건 | C9: 11月中旬／前金30% 仮 | D9: 中 | E9: サプライヤー契約 ／ 공급사 계약 | F9: 月別シートの山の位置が変わります ／ 월별 시트의 피크 위치가 바뀝니다
A10: 6 | B10: 為替レート 환율 | C10: 0.11円/W | D10: 小 | E10: 当日レート ／ 당일 환율 | F10: ±10%で総額が±約160万円動きます ／ ±10%로 총액 ±약 160만엔
A11: 注記
A12: 00_前提_전제 の黄色セルを書き換えると、全シートが自動で再計算されます。
A13: 00_前提_전제 의 노란색 셀을 바꾸면 모든 시트가 자동으로 재계산됩니다.

Sheet 00_前提_전제
A1: 前提 ／ 전제
A2: 黄色セルが入力欄です。／ 노란색 셀이 입력란입니다.
A4: 項目 항목 | B4: 値 값 | C4: 単位 단위 | D4: 円換算 엔 환산 | E4: 根拠 근거
A5: 為替レート 환율 | B5: 0.11 | C5: 円/W | E5: 1円≒9.09ウォン ／ 1엔≒9.09원
A6: 対象月数 대상 개월수 | B6: 3 | C6: ヶ月 | E6: 2026-10 〜 2026-12 ／ 2026-10 ~ 2026-12
A7: 800個 発注数量 800개 발주수량 | B7: 800 | C7: 個 | E7: 通関士見積の対象 ／ 통관사 견적 대상
A8: 800個 通関費/個 800개 통관비/개 | B8: 1000 | C8: 円/個 | D8: =IF($C8="W/個",B8*$B$5,B8) -> 1000 | E8: ★見積未提示。積み上げ試算 ／ ★견적 미제출. 적산 추정
A9: 800個 平均仕入原価 800개 평균 매입원가 | B9: 140000 | C9: W/個 | D9: =IF($C9="W/個",B9*$B$5,B9) -> 15400 | E9: 仮ミックス S40:M40:L20 ／ 가정 믹스
A11: 注記
A12: 為替・月数・800個の通関費を変えると、全シートが自動で再計算されます。
A13: 환율·개월수·800개 통관비를 바꾸면 모든 시트가 자동으로 재계산됩니다.
