Workbook

Sheet 次回支払い算出
A1: LIBETEE KOREA 次回支払い 算出
A2: 算出日: 2026-09-08 ／ 通貨: 韓国ウォン（KRW）／ 700個の大量入荷分は算出対象外
A4: ① 確定・固定分（金額が確定している支払い）
A5: 区分 | B5: 項目 | C5: 数量・基準 | D5: 金額（ウォン） | F5: 根拠・備考
A6: マーケティング | B6: 7/18～8/19 マーケティング費用 | C6: 1か月 | D6: ='今後の予想費用'!D4 -> 3960000 | F6: 付加価値税込み／「今後の予想費用」D4
A7: 輸入・通関 | B7: 今回入荷スーツケース S | C7: 18個 × 100,000 | D7: ='スーツケース_仕入状況'!D12 -> 1800000 | F7: 「スーツケース_仕入状況」D12
A8: 輸入・通関 | B8: 今回入荷スーツケース M | C8: 15個 × 150,000 | D8: ='スーツケース_仕入状況'!D13 -> 2250000 | F8: 「スーツケース_仕入状況」D13
A9: 人件費 | B9: 給与 | C9: 月1回 | D9: ='今後の予想費用'!E9 -> 3000000 | F9: 月給300万ウォン基準
A10: 固定費 | B10: 家賃 | C10: 月1回 | D10: ='今後の予想費用'!E7 -> 550000 | F10: 既存の月間支出基準
A11: 運営費 | B11: 管理費 | C11: 月1回 | D11: ='今後の予想費用'!E10 -> 165000 | F11: 既存の月間支出基準
A12: 固定費 | B12: 税理士費用 | C12: 月1回 | D12: ='今後の予想費用'!E8 -> 110000 | F12: 既存の月間支出基準
A13: ① 確定・固定分 小計 | D13: =SUM(D6:D12) -> 11835000
A15: ② 変動費（過去実績の1回あたり平均から予想）
A16: 区分 | B16: 項目 | C16: 数量・基準 | D16: 金額（ウォン） | F16: 根拠・備考
A17: 交通・出張 | B17: 交通費 | C17: 実績770,000÷3回 | D17: =770000/3 -> 256666.67 | F17: 2026-06/07/08 に発生
A18: 配送・物流 | B18: 宅配費 | C18: 実績420,300÷7回 | D18: =420300/7 -> 60042.857 | F18: 2026-03～08 に発生
A19: 配送・物流 | B19: EMS | C19: 実績688,400÷4回 | D19: =688400/4 -> 172100 | F19: 2026-01/02/03/05 に発生
A20: マーケティング | B20: 広告費（通常運用分） | C20: 実績390,000÷3回 | D20: =390000/3 -> 130000 | F20: 2026-03/06/07 に発生。①のマーケ費とは別枠
A21: ソフトウェア | B21: Canva ほか | C21: 実績29,700÷3回 | D21: =29700/3 -> 9900 | F21: 2026-06/07/08 に発生
A22: その他事業費 | B22: Instagram・その他 | C22: 実績108,500÷5回 | D22: =108500/5 -> 21700 | F22: 2025-12, 2026-02/06/07/08 に発生
A23: ② 変動費 小計（予想） | D23: =SUM(D17:D22) -> 650409.52
A25: ③ 次回支払い 合計
B26: 確定・固定分（①） | D26: =D13 -> 11835000 | F26: 金額確定分
B27: 変動費 予想（②） | D27: =D23 -> 650409.52 | F27: 過去実績平均。実績確定後に差し替え
B28: 次回支払い 合計見込み | D28: =D26+D27 -> 12485410 | F28: ①＋②
A30: ④ 支払後の累計（参考）
B31: 総支出合計（「支出詳細」計上ベース） | D31: ='支出詳細'!C41 -> 46418850 | F31: 既存事業支出＋追加給与＋スーツケース原価
B32: うち未払い（今回入荷スーツケース原価） | D32: =-'スーツケース_仕入状況'!D14 -> -4050000 | F32: ①に含まれるため二重計上を控除
B33: 支払済み累計 | D33: =D31+D32 -> 42368850 | F33: 2025.12～2026.08 の支払済み
B34: 次回支払い 合計見込み | D34: =D28 -> 12485410 | F34: ③より
B35: 次回支払い後の累計見込み | D35: =D33+D34 -> 54854260
A37: ⑤ 円換算（参考・レートは手入力）
B38: 為替レート（1ウォン = ○円） | D38: 0.11 | F38: ※ 仮の参考レート。必ず最新レートに更新してください（黄色＝入力セル）
B39: 次回支払い 合計見込み（円） | D39: =D28*D38 -> 1373395
A41: 注記・前提
A42: 1. 700個の大量入荷分は、原案どおり今回の算出から除外しています。
A43: 2. 「今回入荷スーツケース原価 4,050,000ウォン」は「支出詳細」の総支出合計に既に計上されているため、④では二重計上を避けて控除しています。
A44: 3. ②の変動費は過去実績の1回あたり平均による予想値です（青字＝手入力の前提値）。実績が確定したら差し替えてください。
A45: 4. 「リベティ_支出状況」の最終総支出 37,875,450 と「支出詳細」の明細合計 37,768,850 に 106,600ウォンの差異があります（月次合計ベースと明細合計ベースの差）。要確認。
A46: 5. 緑字＝他シート参照、青字＝手入力の前提値、黄色セル＝更新が必要な入力欄。

Sheet 販売価格・利益計算
A1: LIBETEE KOREA 販売価格・1個あたり利益計算
A2: 通貨: 日本円（JPY）／ 原価は韓国ウォン建てを為替レートで換算
A4: ① 前提条件（黄色セル＝入力欄）
B5: 為替レート（1ウォン = ○円） | C5: ='次回支払い算出'!D38 -> 0.11 | J5: 「次回支払い算出」D38と連動。実レートに更新してください
B6: 決済・販売手数料率 | C6: 0.04 | J6: ご指定の4%
B7: 送料（円／個） | C7: 300 | J7: ご指定の300円
A9: ② サイズ別 1個あたり利益
A10: サイズ | B10: 販売状態 | C10: 販売価格(円) | D10: 手数料(4%) | E10: 送料(円) | F10: 原価(ウォン) | G10: 原価(円) | H10: 粗利(円) | I10: 粗利率 | J10: 備考
A11: S | B11: 在庫あり（18個） | C11: 21900 | D11: =C11*$C$6 -> 876 | E11: =$C$7 -> 300 | F11: ='スーツケース_仕入状況'!C12 -> 100000 | G11: =F11*$C$5 -> 11000 | H11: =C11-D11-E11-G11 -> 9724 | I11: =IFERROR(H11/C11,0) -> 0.44401826 | J11: ご指定の販売価格。原価は今回入荷分S単価
A12: M | B12: 在庫あり（15個） | C12: 27900 | D12: =C12*$C$6 -> 1116 | E12: =$C$7 -> 300 | F12: ='スーツケース_仕入状況'!C13 -> 150000 | G12: =F12*$C$5 -> 16500 | H12: =C12-D12-E12-G12 -> 9984 | I12: =IFERROR(H12/C12,0) -> 0.35784946 | J12: ご指定の販売価格。原価は今回入荷分M単価
A13: L | B13: 予約注文（在庫なし・入荷待ち） | C13: 33900 | D13: =C13*$C$6 -> 1356 | E13: =$C$7 -> 300 | F13: 200000 | G13: =F13*$C$5 -> 22000 | H13: =C13-D13-E13-G13 -> 10244 | I13: =IFERROR(H13/C13,0) -> 0.30218289 | J13: ★ 販売価格・原価とも未指定のため仮置き。要確定
A15: ③ 今回入荷33個（S18・M15）を完売した場合 ※Lは在庫なしのため除外
A16: サイズ | B16: 数量 | C16: 1個あたり粗利(円) | D16: 粗利合計(円) | J16: 備考
A17: S | B17: ='スーツケース_仕入状況'!B12 -> 18 | C17: =H11 -> 9724 | D17: =B17*C17 -> 175032
A18: M | B18: ='スーツケース_仕入状況'!B13 -> 15 | C18: =H12 -> 9984 | D18: =B18*C18 -> 149760
A19: 合計 | B19: =SUM(B17:B18) -> 33 | D19: =SUM(D17:D18) -> 324792
A21: ④ 次回支払いとの比較・損益分岐
B22: 次回支払い 合計見込み（円） | D22: ='次回支払い算出'!D39 -> 1373395 | J22: 「次回支払い算出」③×為替レート
B23: 33個完売時の粗利合計（円） | D23: =D19 -> 324792 | J23: ③より
B24: 次回支払いのカバー率 | D24: =IFERROR(D23/D22,0) -> 0.2364884 | J24: 33個では次回支払いを賄えません
B25: 不足額（円） | D25: =D22-D23 -> 1048603 | J25: 追加販売で埋める必要がある金額
B26: S:M=18:15 構成の平均粗利（円/個） | D26: =IFERROR(D19/B19,0) -> 9842.1818 | J26: ③の加重平均
B27: 損益分岐 必要販売数（S単独） | D27: =ROUNDUP(D22/H11,0) -> 142 | J27: 次回支払いを粗利で回収するのに必要な個数
B28: 損益分岐 必要販売数（M単独） | D28: =ROUNDUP(D22/H12,0) -> 138
B29: 損益分岐 必要販売数（18:15構成） | D29: =ROUNDUP(D22/D26,0) -> 140
A32: 注記・前提
A33: 1. 販売価格（S 21,900円／M 27,900円）、手数料率4%、送料300円／個はご指定の値です。
A34: 2. L は在庫がないため「予約注文（入荷待ち）」として計上。販売価格・原価はご指定がないため仮置きです（黄色セル）。確定値に置き換えてください。
A35: 3. 原価は S 100,000ウォン／M 150,000ウォン（「スーツケース_仕入状況」参照）を為替レートで円換算しています。レートは①のC5セル（「次回支払い算出」D38と連動）。
A36: 4. 粗利は 販売価格 −手数料 −送料 −原価 のみを引いた商品単位の粗利です。広告費・人件費・家賃などの固定費は含みません（それらは「次回支払い算出」側で計上）。
A37: 5. 手数料4%は販売価格（税込）に対する率として計算しています。税抜ベースが正の場合はご連絡ください。
A38: 6. 緑字＝他シート参照、青字＝入力値、黄色セル＝要確定の入力欄。

Sheet リベティ_支出状況
A1: LIBETEE KOREA 事業費支出まとめ（2025.12～2026.08）
A3: 主要指標 | B3: 金額
A4: 既存事業支出合計 | B4: 29875450
A5: 追加給与 | B5: 8000000
A6: 最終総支出 | B6: 37875450
A7: 集計期間 | B7: 2025.12 ~ 2026.08
A8: 月 | B8: 事業支出（ウォン）
A9: 2025-12 | B9: 2875000
A10: 2026-01 | B10: 2698900
A11: 2026-02 | B11: 4993000
A12: 2026-03 | B12: 3332000
A13: 2026-04 | B13: 1264050
A14: 2026-05 | B14: 2959000
A15: 2026-06 | B15: 4468900
A16: 2026-07 | B16: 3285600
A17: 2026-08 | B17: 3999000
A19: スーツケース仕入・原価まとめ
A20: 既存仕入 S | B20: 16個 × 100,000ウォン
A21: 既存仕入 M | B21: 20個 × 150,000ウォン
A22: 既存スーツケース原価 合計 | B22: ='スーツケース_仕入状況'!D7 -> 4600000
A23: 今回入荷予定 | B23: S 18個 + M 15個 = 合計33個
A24: 今回入荷予定分 スーツケース原価 | B24: ='スーツケース_仕入状況'!D14 -> 4050000
A25: スーツケース原価を含む最終支出合計 | B25: =B6+B22+B24 -> 46525450
A26: 今後700個入荷予定 | B26: 今回の計算から除外
A27: ※ 上記は「支出詳細」シートの総支出合計 46,418,850 と 106,600 ウォンの差異あり（月次合計ベースと明細合計ベースの差／要確認）

Sheet 支出詳細
A1: LIBETEE KOREA 支出詳細 — 同一支払先合算
A3: 区分 | B3: 支払先／項目 | C3: 総支出額（ウォン） | D3: 発生回数 | E3: 発生月
A4: 人件費 | B4: ソヒョン、ウンソン | C4: 11500000 | D4: 7 | E4: 2026-01, 2026-02, 2026-03, 2026-05, 2026-06, 2026-07, 2026-08
A5: 人件費 | B5: ココ | C5: 8000000 | D5: 1 | E5: 追加反映
A6: 賃貸・管理 | B6: 家賃 | C6: 4950000 | D6: 9 | E6: 2025-12, 2026-01, 2026-02, 2026-03, 2026-04, 2026-05, 2026-06, 2026-07, 2026-08
A7: 賃貸・管理 | B7: 管理費 | C7: 1320000 | D7: 8 | E7: 2026-01, 2026-02, 2026-03, 2026-04, 2026-05, 2026-06, 2026-07, 2026-08
A8: 設備 | B8: パソコン | C8: 1100000 | D8: 1 | E8: 2025-12
A9: ストア・サイト | B9: 自社ECサイト | C9: 1100000 | D9: 1 | E9: 2026-02
A10: 輸入・通関 | B10: 輸入費 | C10: 1065000 | D10: 1 | E10: 2026-02
A11: 交通・出張 | B11: 航空券 | C11: 980000 | D11: 2 | E11: 2026-06, 2026-08
A12: 撮影・コンテンツ | B12: 撮影データ | C12: 935000 | D12: 1 | E12: 2026-03
A13: 税務・行政 | B13: 税理士 | C13: 880000 | D13: 8 | E13: 2026-01, 2026-02, 2026-03, 2026-04, 2026-05, 2026-06, 2026-07, 2026-08
A14: 交通・出張 | B14: 交通費 | C14: 770000 | D14: 3 | E14: 2026-07, 2026-08, 2026-06
A15: 配送・物流 | B15: EMS | C15: 688400 | D15: 4 | E15: 2026-01, 2026-02, 2026-03, 2026-05
... A30: レビュー・プロモーション | B30: ビズウォレット フォトレビュー | C30: 60000 | D30: 1 | E30: 2026-08
A31: 商品原価 | B31: 既存仕入スーツケース原価（S 16個 / M 20個） | C31: ='スーツケース_仕入状況'!D7 -> 4600000 | D31: 1 | E31: 現在までの仕入分 | F31: 提供分および日本からのEMS発送分を除外
A32: 商品原価 | B32: 今回入荷予定スーツケース原価（S 18個 / M 15個） | C32: ='スーツケース_仕入状況'!D14 -> 4050000 | D32: 1 | E32: 今回入荷予定 | F32: 700個の大量入荷分を除外
A33: 税務・行政 | B33: 登録免許税 | C33: 40500 | D33: 1 | E33: 2026-01
A34: ストア・サイト | B34: サイト | C34: 39000 | D34: 1 | E34: 2026-03
A35: 撮影・コンテンツ | B35: スタジオ | C35: 36000 | D35: 1 | E35: 2026-08
A36: ソフトウェア | B36: Canva | C36: 29700 | D36: 3 | E36: 2026-06, 2026-07, 2026-08
A37: ストア・サイト | B37: ドメイン | C37: 16000 | D37: 1 | E37: 2026-02
A38: ソフトウェア | B38: Photoshop | C38: 5000 | D38: 1 | E38: 2026-05
A39: ソフトウェア | B39: VLO | C39: 2900 | D39: 1 | E39: 2026-07
A41: 総支出合計 | C41: =SUM(C4:C39) -> 46418850

Sheet 今後の予想費用
A1: LIBETEE KOREA 今後必要となる費用予想
A3: 区分 | B3: 内容 | C3: 数量／期間 | D3: 確定金額（ウォン） | E3: 予想金額（ウォン） | F3: 備考
A4: マーケティング | B4: 7/18～8/19 マーケティング費用 | C4: 1か月 | D4: 3960000 | F4: 付加価値税込み
A5: 輸入・通関 | B5: 今回入荷予定スーツケース（S 18個 / M 15個） | C5: 合計33個 | D5: ='スーツケース_仕入状況'!D14 -> 4050000 | F5: 今回入荷予定33個のスーツケース原価（S 18個 / M 15個）
A6: 輸入・通関 | B6: 今後入荷予定スーツケース | C6: 700個 | F6: 今回の予想費用計算から除外
A7: 固定費 | B7: 家賃 | C7: 月1回 | E7: 550000 | F7: 既存の月間支出基準
A8: 固定費 | B8: 税理士費用 | C8: 月1回 | E8: 110000 | F8: 既存の月間支出基準
A9: 人件費 | B9: 給与 | C9: 月1回 | E9: 3000000 | F9: 月給300万ウォン基準
A10: 運営費 | B10: 管理費 | C10: 月1回 | E10: 165000 | F10: 既存の月間支出基準
A11: 運営費 | B11: 交通費 | C11: 月間予想 | F11: 変動費
A12: 配送・物流 | B12: 宅配・EMS費用 | C12: 月間予想 | F12: 販売量により変動
A13: 広告・マーケティング | B13: 今後の広告費 | C13: 月間予想 | F13: 追加実施時に入力
A14: その他 | B14: その他運営費 | C14: 月間予想 | F14: ソフトウェア・撮影・印刷など
A16: 仮配送・レビュー | F16: 1個あたりのスーツケース原価：S 100,000ウォン / M 150,000ウォン
A17: 現時点で確認可能な今後の費用合計 | D17: =D4+D5+E7+E8+E9+E10 -> 11835000

Sheet スーツケース_仕入状況
A1: LIBETEE KOREA スーツケース輸入・原価状況
A3: 現在までに輸入したスーツケース — 提供分および日本からのEMS発送分を除外
A4: サイズ | B4: 数量 | C4: 1個あたり原価（ウォン） | D4: スーツケース原価合計（ウォン） | E4: 算入基準 | F4: 備考
A5: S | B5: 16 | C5: 100000 | D5: 1600000 | E5: 実際の輸入分 | F5: 提供分および日本EMS発送分を除外
A6: M | B6: 20 | C6: 150000 | D6: 3000000 | E6: 実際の輸入分 | F6: 提供分および日本EMS発送分を除外
A7: 現在までのスーツケース原価合計 | D7: 4600000
A10: 今回入荷予定 — 合計33個
A11: サイズ | B11: 数量 | C11: 参考原価（ウォン） | D11: 参考スーツケース原価（ウォン） | E11: 入荷状況 | F11: 備考
A12: S | B12: 18 | C12: 100000 | D12: 1800000 | E12: 入荷予定 | F12: 33個のうちS 18個
A13: M | B13: 15 | C13: 150000 | D13: 2250000 | E13: 入荷予定 | F13: 33個のうちM 15個
A14: 33個分 参考スーツケース原価 合計 | D14: 4050000
A15: 700個入荷前までのスーツケース原価 合計 | D15: 8650000
A17: 今後の入荷計画
A18: 区分 | B18: 数量 | C18: 原価 | D18: スーツケース原価 | E18: 状況 | F18: 備考
A19: 今後の大量入荷 | B19: 700 | E19: 予定 | F19: 今回の原価・予想費用の計算から除外
