Workbook

Sheet ① 概要
A1: リベティ 多機能スーツケース｜SEO・ブログ運用 管理表
A2: 目的：ビッグワード検索でリベティがヒットし、生成AI(ChatGPT等)にも拾われる状態をつくる／広告でクリックを誘発しCVへ
A4: ■ 目的（ゴール）
A5: 1. 「多機能スーツケース」「機内持ち込み」「フロントオープン」「スーツケース」「キャリーケース」「キャスターロック」等のビッグワードでリベティを上位表示。
A6: 2. ブログに広告をかけてクリックを誘発 → 自社サイトへ送客しCV。
A7: 3. ChatGPT等の生成AIが回答時にリベティを引用・推奨する状態（LLMO/AEO対策）をつくる。
A9: ■ 現状（スタート地点）
A10: ・ブログ配信：なし（＝これから資産をゼロから構築）
A11: ・PR TIMES：運用中（＝③の土台あり。被リンク源として活用）
A12: ・Google広告：キーワードのみ（＝写真/ディスプレイ広告は未着手）
A14: ■ 3つの運用タイプ（詳細は『③ 3運用タイプ』シート）
A15: ①自社・写真広告：自社ブログで商品を主役に。商品写真・バナーで訴求しGoogle写真広告と連動。
... A29: ■ 進捗ダッシュボード（各商品シートから自動集計）
A30: 商品シート | B30: 計画記事数 | C30: 公開済み | D30: 執筆中 | E30: 未着手 | F30: 公開率
A31: PCスーツケース | B31: =COUNTA('PCスーツケース'!$B$5:$B$60) | C31: =COUNTIF('PCスーツケース'!$N$5:$N$60,"公開済み") | D31: =COUNTIF('PCスーツケース'!$N$5:$N$60,"執筆中") | E31: =COUNTIF('PCスーツケース'!$N$5:$N$60,"未着手") | F31: =IFERROR(C31/B31,0)
A32: クラシックアルミニウムスーツケース | B32: =COUNTA('クラシックアルミニウムスーツケース'!$B$5:$B$60) | C32: =COUNTIF('クラシックアルミニウムスーツケース'!$N$5:$N$60,"公開済み") | D32: =COUNTIF('クラシックアルミニウムスーツケース'!$N$5:$N$60,"執筆中") | E32: =COUNTIF('クラシックアルミニウムスーツケース'!$N$5:$N$60,"未着手") | F32: =IFERROR(C32/B32,0)
A33: 多機能アルミニウムスーツケース | B33: =COUNTA('多機能アルミニウムスーツケース'!$B$5:$B$60) | C33: =COUNTIF('多機能アルミニウムスーツケース'!$N$5:$N$60,"公開済み") | D33: =COUNTIF('多機能アルミニウムスーツケース'!$N$5:$N$60,"執筆中") | E33: =COUNTIF('多機能アルミニウムスーツケース'!$N$5:$N$60,"未着手") | F33: =IFERROR(C33/B33,0)
A34: ジップタイプスーツケース | B34: =COUNTA('ジップタイプスーツケース'!$B$5:$B$60) | C34: =COUNTIF('ジップタイプスーツケース'!$N$5:$N$60,"公開済み") | D34: =COUNTIF('ジップタイプスーツケース'!$N$5:$N$60,"執筆中") | E34: =COUNTIF('ジップタイプスーツケース'!$N$5:$N$60,"未着手") | F34: =IFERROR(C34/B34,0)
A35: 留学アウトドアスーツケース | B35: =COUNTA('留学アウトドアスーツケース'!$B$5:$B$60) | C35: =COUNTIF('留学アウトドアスーツケース'!$N$5:$N$60,"公開済み") | D35: =COUNTIF('留学アウトドアスーツケース'!$N$5:$N$60,"執筆中") | E35: =COUNTIF('留学アウトドアスーツケース'!$N$5:$N$60,"未着手") | F35: =IFERROR(C35/B35,0)
A36: 合計 | B36: =SUM(B31:B35) | C36: =SUM(C31:C35) | D36: =SUM(D31:D35) | E36: =SUM(E31:E35) | F36: =IFERROR(C36/B36,0)

Sheet ② キーワード戦略
A1: キーワード戦略｜ビッグワードでリベティをヒットさせる設計
A2: ビッグワード単体は競合が強い→『ビッグワード×商品特徴』の掛け合わせと、比較・まとめ記事で面を取る。検索ボリュームは目安(大/中/小)。正確な数値はキーワードプランナーで要確認。
A4: 区分 | B4: 対策キーワード | C4: 掛け合わせ例（ロングテール） | D4: 検索意図 | E4: ボリューム目安 | F4: 難易度 | G4: 主担当商品シート | H4: 獲りにいく記事タイプ
A5: ビッグ | B5: スーツケース | C5: スーツケース おすすめ / 選び方 / 初めて | D5: 比較検討 | E5: 大 | F5: 高 | G5: 全商品（まとめ） | H5: ピラー：選び方ガイド＋比較まとめ
A6: ビッグ | B6: 多機能スーツケース | C6: 多機能スーツケース 比較 / 機能 | D6: 機能重視 | E6: 中 | F6: 高 | G6: 多機能アルミニウム | H6: 機能特化の比較・解説
A7: ビッグ | B7: 機内持ち込み | C7: 機内持ち込み サイズ / 対応 / lcc | D7: 具体検討・CV近 | E7: 大 | F7: 高 | G7: PC / ジップ | H7: サイズ対応表＋対応モデル紹介
A8: ビッグ | B8: フロントオープン | C8: フロントオープン スーツケース / pc | D8: 機能指名 | E8: 中 | F8: 中 | G8: PCスーツケース | H8: フロントオープンの利点＋実演
A9: ビッグ | B9: キャリーケース | C9: キャリーケース 軽量 / 機内 / 大型 | D9: 比較検討 | E9: 大 | F9: 高 | G9: ジップ / 留学 | H9: タイプ別比較・用途別おすすめ
A10: ビッグ | B10: キャスターロック | C10: キャスターロック スーツケース / 便利 | D10: 機能訴求 | E10: 小 | F10: 低 | G10: 多機能アルミ / クラシック | H10: キャスターロックの必要性＋搭載モデル
A11: 特徴 | B11: アルミ スーツケース | C11: アルミ スーツケース 高級 / 丈夫 / 軽量 | D11: 品質重視 | E11: 中 | F11: 中 | G11: クラシック/多機能アルミ | H11: アルミの魅力＋ボーケン試験
A12: 特徴 | B12: スーツケース 大型 | C12: 大型 スーツケース 留学 / 長期 | D12: 大容量ニーズ | E12: 中 | F12: 中 | G12: 留学アウトドア | H12: 容量別の選び方
A13: 用途 | B13: スーツケース 出張 | C13: 出張 スーツケース ビジネス / pc収納 | D13: ビジネス | E13: 中 | F13: 中 | G13: PCスーツケース | H13: 出張特化ガイド
A14: 用途 | B14: スーツケース 留学 | C14: 留学 スーツケース おすすめ / 大容量 | D14: 長期渡航 | E14: 中 | F14: 中 | G14: 留学アウトドア | H14: 留学準備ガイド
A16: ※ ビッグワードは単体で狙わず『掛け合わせ』で入口を作り、内部リンクでピラー(選び方まとめ)へ集約。まとめ記事に各商品への内部リンクを張ることで、指名検索前の面を確保する。

Sheet ③ 3運用タイプ
A1: 3つの運用タイプ｜役割・訴求・広告・コンプラ
A2: 同じ商品でも『誰の目線で・どの媒体で・どの広告で』出すかを分けて設計する。
B4: ①自社・写真広告 | C4: ②第三者・アフィリ | D4: ③PR TIMES
A5: 狙い | B5: 自社商品を主役に直接CV | C5: 中立比較で信頼→CV＋アフィリ収益 | D5: ニュース化で権威付け・被リンク
A6: 媒体 | B6: 自社ブログ | C6: 自社ブログ（比較カテゴリ） | D6: PR TIMES → 自社ブログへ送客
A7: 目線・トーン | B7: ブランド発信・商品愛 | C7: 客観・中立（長所も短所も） | D7: 報道スタイル・事実ベース
A8: 主担当 | B8: 北野（雪乃） | C8: 西岡・雪乃 | D8: 北野
A9: 広告 | B9: 商品写真バナー＋Google写真広告(P-MAX/ディスプレイ) | C9: 記事内アフィリリンク＋Google検索広告 | D9: リリース配信＋SNS拡散
A10: CTA・リンク先 | B10: 自社ECの商品ページ | C10: 比較ページ（自社＋他社アフィリ） | D10: 自社ブログ検証記事→EC
A11: 収益 | B11: 自社売上 | C11: 自社売上＋アフィリ報酬 | D11: （間接）指名検索・被リンクでSEO底上げ
A12: KPI | B12: CTR・CVR・ROAS | C12: クリック率・アフィリ発生/承認 | D12: 掲載数・被リンク数・参照流入
A13: コンプラ注意 | B13: 景表法（優良誤認NG） | C13: ★PR表記必須（ステマ規制）／捏造NG | D13: 事実のみ・試験は実施分のみ

Sheet PCスーツケース
A1: PCスーツケース
A2: ターゲット：出張の多いビジネス層／訴求：フロントオープン・PC収納・機内持ち込み・充電
A4: No. | B4: 対策KW(主) | C4: 掛け合わせビッグワード | D4: 検索意図 | E4: Vol目安 | F4: 難易度 | G4: 記事タイトル案 | H4: URLスラッグ | I4: 運用タイプ | J4: 担当 | K4: 想定文字数 | L4: CTA・リンク先 | M4: 公開予定日 | N4: ステータス
A5: 1 | B5: フロントオープン | C5: フロントオープン スーツケース | D5: 機能指名 | E5: 中 | F5: 中 | G5: 【実演】フロントオープンPCスーツケースが出張で神な理由 | H5: pc-front-open | I5: ①自社・写真広告 | J5: 雪乃 | K5: 4000 | L5: 自社EC 商品ページ | N5: 未着手
A6: 2 | B6: 機内持ち込み | C6: 機内持ち込み pc スーツケース | D6: CV近 | E6: 大 | F6: 高 | G6: 機内持ち込みOK×PC収納｜出張で選ぶべき1台 | H6: pc-carry-on | I6: ①自社・写真広告 | J6: 雪乃 | K6: 5000 | L6: 自社EC 商品ページ | N6: 未着手
A7: 3 | B7: スーツケース 出張 | C7: 出張 スーツケース ビジネス | D7: ビジネス | E7: 中 | F7: 中 | G7: 出張族が本気で選ぶスーツケース比較｜PC・充電・軽さ | H7: business-suitcase-compare | I7: ②第三者・アフィリ | J7: 西岡 | K7: 6000 | L7: 比較ページ(自社+他社) | N7: 未着手
A8: 4 | B8: キャリーケース | C8: キャリーケース ビジネス 軽量 | D8: 比較 | E8: 大 | F8: 高 | G8: ビジネスキャリーケースおすすめ｜PC派の失敗しない選び方 | H8: business-carrycase | I8: ②第三者・アフィリ | J8: 雪乃 | K8: 6000 | L8: 比較ページ | N8: 未着手
A9: 5 | B9: スーツケース usb | C9: usb スーツケース 充電 | D9: 機能訴求 | E9: 小 | F9: 低 | G9: USBポート付きスーツケースは必要？メリットと注意点 | H9: suitcase-usb | I9: ①自社・写真広告 | J9: 西岡 | K9: 3500 | L9: 自社EC 商品ページ | N9: 未着手
A10: 6 | B10: 新商品PR | C10: リベティ pc スーツケース 新発売 | D10: 指名・話題 | E10: 小 | F10: 低 | G10: 【新発売】ビジネス特化PCスーツケースを発表 | H10: prtimes-pc-launch | I10: ③PR TIMES | J10: 北野 | K10: 1500 | L10: 自社ブログ→EC | N10: 未着手
A12: 凡例：アンバー列(公開予定日・ステータス)を随時更新。運用タイプ/担当/難易度/Vol/ステータスはプルダウン選択。Vol目安=大中小(正確値はキーワードプランナーで確認)。

Sheet クラシックアルミニウムスーツケース
A1: クラシックアルミニウムスーツケース
A2: ターゲット：品質・所有欲を重視する層／訴求：アルミの高級感・丈夫さ(ボーケン試験)・キャスターロック
A4: No. | B4: 対策KW(主) | C4: 掛け合わせビッグワード | D4: 検索意図 | E4: Vol目安 | F4: 難易度 | G4: 記事タイトル案 | H4: URLスラッグ | I4: 運用タイプ | J4: 担当 | K4: 想定文字数 | L4: CTA・リンク先 | M4: 公開予定日 | N4: ステータス
A5: 1 | B5: アルミ スーツケース | C5: アルミ スーツケース 高級 | D5: 品質・所有欲 | E5: 中 | F5: 中 | G5: 一生モノのアルミスーツケース｜クラシックの魅力と選び方 | H5: classic-aluminum | I5: ①自社・写真広告 | J5: 雪乃 | K5: 4500 | L5: 自社EC 商品ページ | N5: 未着手
A6: 2 | B6: スーツケース 丈夫 | C6: スーツケース 丈夫 壊れない アルミ | D6: 不安解消・CV近 | E6: 中 | F6: 中 | G6: 【検証】アルミは本当に丈夫？ボーケン試験で確かめた | H6: aluminum-boken-test | I6: ②第三者・アフィリ | J6: 西岡 | K6: 6000 | L6: 比較ページ | N6: 未着手
A7: 3 | B7: アルミ スーツケース デメリット | C7: アルミ スーツケース 重い デメリット | D7: 比較検討 | E7: 小 | F7: 低 | G7: アルミスーツケースのデメリットと後悔しない選び方 | H7: aluminum-demerit | I7: ②第三者・アフィリ | J7: 西岡 | K7: 5000 | L7: 比較ページ | N7: 未着手
A8: 4 | B8: キャスターロック | C8: キャスターロック アルミ スーツケース | D8: 機能訴求 | E8: 小 | F8: 低 | G8: キャスターロックは必要？坂道・電車で差が出る理由 | H8: caster-lock | I8: ①自社・写真広告 | J8: 雪乃 | K8: 3500 | L8: 自社EC 商品ページ | N8: 未着手
A9: 5 | B9: スーツケース 高級 ブランド | C9: 高級 スーツケース 比較 | D9: ブランド比較 | E9: 中 | F9: 高 | G9: 高級スーツケース比較｜価格に見合う「丈夫さ」の見抜き方 | H9: luxury-suitcase-compare | I9: ②第三者・アフィリ | J9: 西岡 | K9: 6500 | L9: 比較ページ | N9: 未着手
A10: 6 | B10: 品質PR | C10: リベティ アルミ ボーケン 合格 | D10: 権威付け | E10: 小 | F10: 低 | G10: 【品質証明】アルミスーツケースが第三者試験に合格 | H10: prtimes-aluminum-quality | I10: ③PR TIMES | J10: 北野 | K10: 1500 | L10: 自社ブログ→EC | N10: 未着手
A12: 凡例：アンバー列(公開予定日・ステータス)を随時更新。運用タイプ/担当/難易度/Vol/ステータスはプルダウン選択。Vol目安=大中小(正確値はキーワードプランナーで確認)。

Sheet 多機能アルミニウムスーツケース
A1: 多機能アルミニウムスーツケース
A2: ターゲット：機能を比較して選ぶ層／訴求：多機能スーツケース・キャスターロック・機内持ち込み(コアKW)
A4: No. | B4: 対策KW(主) | C4: 掛け合わせビッグワード | D4: 検索意図 | E4: Vol目安 | F4: 難易度 | G4: 記事タイトル案 | H4: URLスラッグ | I4: 運用タイプ | J4: 担当 | K4: 想定文字数 | L4: CTA・リンク先 | M4: 公開予定日 | N4: ステータス
A5: 1 | B5: 多機能スーツケース | C5: 多機能スーツケース アルミ 比較 | D5: 機能重視 | E5: 中 | F5: 高 | G5: 多機能スーツケースとは？「全部入り」アルミを徹底解剖 | H5: multifunction-suitcase | I5: ①自社・写真広告 | J5: 西岡 | K5: 5000 | L5: 自社EC 商品ページ | N5: 未着手
A6: 2 | B6: 多機能スーツケース | C6: 多機能 スーツケース おすすめ ランキング | D6: 比較・CV近 | E6: 中 | F6: 高 | G6: 多機能スーツケースおすすめ比較｜機能で選ぶ完全ガイド | H6: multifunction-ranking | I6: ②第三者・アフィリ | J6: 西岡 | K6: 7000 | L6: 比較ページ | N6: 未着手
A7: 3 | B7: キャスターロック | C7: キャスターロック スーツケース 便利 | D7: 機能訴求 | E7: 小 | F7: 低 | G7: キャスターロック＋TSA＋拡張｜多機能の便利機能まとめ | H7: multifunction-features | I7: ①自社・写真広告 | J7: 雪乃 | K7: 4000 | L7: 自社EC 商品ページ | N7: 未着手
A8: 4 | B8: 機内持ち込み | C8: 多機能 スーツケース 機内持ち込み | D8: CV近 | E8: 大 | F8: 高 | G8: 多機能なのに機内持ち込みOK｜出張で最強の1台 | H8: multifunction-carryon | I8: ①自社・写真広告 | J8: 雪乃 | K8: 4500 | L8: 自社EC 商品ページ | N8: 未着手
A9: 5 | B9: スーツケース 機能 比較 | C9: スーツケース 機能 比較 表 | D9: 比較 | E9: 中 | F9: 中 | G9: スーツケースの機能を一覧比較｜どこまで必要? | H9: suitcase-feature-compare | I9: ②第三者・アフィリ | J9: 西岡 | K9: 6000 | L9: 比較ページ | N9: 未着手
A10: 6 | B10: 新機能PR | C10: リベティ 多機能 スーツケース 新機能 | D10: 話題化 | E10: 小 | F10: 低 | G10: 【新発売】キャスターロック搭載の多機能アルミを発表 | H10: prtimes-multifunction | I10: ③PR TIMES | J10: 北野 | K10: 1500 | L10: 自社ブログ→EC | N10: 未着手
A12: 凡例：アンバー列(公開予定日・ステータス)を随時更新。運用タイプ/担当/難易度/Vol/ステータスはプルダウン選択。Vol目安=大中小(正確値はキーワードプランナーで確認)。

Sheet ジップタイプスーツケース
A1: ジップタイプスーツケース
A2: ターゲット：軽さ・価格・使い勝手重視の層／訴求：軽量・拡張・機内持ち込み・キャリーケース
A4: No. | B4: 対策KW(主) | C4: 掛け合わせビッグワード | D4: 検索意図 | E4: Vol目安 | F4: 難易度 | G4: 記事タイトル案 | H4: URLスラッグ | I4: 運用タイプ | J4: 担当 | K4: 想定文字数 | L4: CTA・リンク先 | M4: 公開予定日 | N4: ステータス
A5: 1 | B5: スーツケース 軽量 | C5: 軽量 スーツケース ジッパー | D5: 軽さ重視 | E5: 大 | F5: 高 | G5: 軽いスーツケースならジップタイプ｜軽量の理由と選び方 | H5: zip-lightweight | I5: ①自社・写真広告 | J5: 雪乃 | K5: 4000 | L5: 自社EC 商品ページ | N5: 未着手
A6: 2 | B6: キャリーケース | C6: キャリーケース 軽量 拡張 | D6: 比較 | E6: 大 | F6: 高 | G6: 拡張できるキャリーケース｜荷物が増えても安心の1台 | H6: expandable-carrycase | I6: ①自社・写真広告 | J6: 雪乃 | K6: 4500 | L6: 自社EC 商品ページ | N6: 未着手
A7: 3 | B7: スーツケース ファスナー フレーム 違い | C7: ジッパー フレーム 比較 | D7: 比較検討 | E7: 中 | F7: 中 | G7: ジッパーvsフレーム徹底比較｜初めてはどっち? | H7: zip-vs-frame | I7: ②第三者・アフィリ | J7: 西岡 | K7: 6000 | L7: 比較ページ | N7: 未着手
A8: 4 | B8: 機内持ち込み | C8: 機内持ち込み 軽量 スーツケース | D8: CV近 | E8: 大 | F8: 高 | G8: 機内持ち込み最軽量級｜LCCでも安心のジップタイプ | H8: zip-carryon-light | I8: ①自社・写真広告 | J8: 雪乃 | K8: 4500 | L8: 自社EC 商品ページ | N8: 未着手
A9: 5 | B9: スーツケース コスパ | C9: コスパ スーツケース おすすめ | D9: 価格重視 | E9: 中 | F9: 中 | G9: コスパ最強スーツケース比較｜安くて丈夫を見抜く | H9: cospa-suitcase | I9: ②第三者・アフィリ | J9: 西岡 | K9: 6000 | L9: 比較ページ | N9: 未着手
A10: 6 | B10: 新色PR | C10: リベティ ジップ スーツケース 新色 | D10: 話題化 | E10: 小 | F10: 低 | G10: 【新色発売】軽量ジップスーツケースにカラー追加 | H10: prtimes-zip-color | I10: ③PR TIMES | J10: 北野 | K10: 1200 | L10: 自社ブログ→EC | N10: 未着手
A12: 凡例：アンバー列(公開予定日・ステータス)を随時更新。運用タイプ/担当/難易度/Vol/ステータスはプルダウン選択。Vol目安=大中小(正確値はキーワードプランナーで確認)。

Sheet 留学アウトドアスーツケース
A1: 留学アウトドアスーツケース
A2: ターゲット：留学・長期・アウトドア層／訴求：大容量・丈夫さ・大型キャリーケース
A4: No. | B4: 対策KW(主) | C4: 掛け合わせビッグワード | D4: 検索意図 | E4: Vol目安 | F4: 難易度 | G4: 記事タイトル案 | H4: URLスラッグ | I4: 運用タイプ | J4: 担当 | K4: 想定文字数 | L4: CTA・リンク先 | M4: 公開予定日 | N4: ステータス
A5: 1 | B5: スーツケース 留学 | C5: 留学 スーツケース おすすめ 大容量 | D5: 長期渡航・CV近 | E5: 中 | F5: 中 | G5: 留学スーツケースの選び方｜大容量・預け入れ完全ガイド | H5: study-abroad-suitcase | I5: ①自社・写真広告 | J5: 雪乃 | K5: 5500 | L5: 自社EC 商品ページ | N5: 未着手
A6: 2 | B6: スーツケース 大型 | C6: 大型 スーツケース 長期旅行 | D6: 大容量ニーズ | E6: 中 | F6: 中 | G6: 大型スーツケース比較｜長期・留学で失敗しない容量選び | H6: large-suitcase-compare | I6: ②第三者・アフィリ | J6: 西岡 | K6: 6500 | L6: 比較ページ | N6: 未着手
A7: 3 | B7: スーツケース 何リットル 留学 | C7: 留学 スーツケース 容量 目安 | D7: サイズ迷い | E7: 小 | F7: 低 | G7: 留学は何リットル?滞在期間別の容量早見表 | H7: study-abroad-liter | I7: ①自社・写真広告 | J7: 雪乃 | K7: 3500 | L7: 自社EC 商品ページ | N7: 未着手
A8: 4 | B8: スーツケース 丈夫 大型 | C8: 丈夫 大型 スーツケース アウトドア | D8: 耐久重視 | E8: 小 | F8: 低 | G8: ハードに使っても壊れない大型スーツケース｜アウトドア対応 | H8: outdoor-durable | I8: ②第三者・アフィリ | J8: 西岡 | K8: 5000 | L8: 比較ページ | N8: 未着手
A9: 5 | B9: キャリーケース 大型 | C9: 大型 キャリーケース 海外 | D9: 海外長期 | E9: 中 | F9: 中 | G9: 海外長期滞在のキャリーケース選び｜移動もラクな大容量 | H9: large-carrycase-overseas | I9: ①自社・写真広告 | J9: 雪乃 | K9: 4500 | L9: 自社EC 商品ページ | N9: 未着手
A10: 6 | B10: 留学特集PR | C10: リベティ 留学 スーツケース 特集 | D10: 季節話題 | E10: 小 | F10: 低 | G10: 【留学シーズン】大容量アウトドアスーツケースを提案 | H10: prtimes-study-abroad | I10: ③PR TIMES | J10: 北野 | K10: 1500 | L10: 自社ブログ→EC | N10: 未着手
A12: 凡例：アンバー列(公開予定日・ステータス)を随時更新。運用タイプ/担当/難易度/Vol/ステータスはプルダウン選択。Vol目安=大中小(正確値はキーワードプランナーで確認)。

Sheet ④ スケジュール
A1: 公開スケジュール（90日ロードマップ）
A2: 『まず面を取る→検証で信頼→広告で加速』の順。週1〜2本を継続。日付は着手時に確定させる。
A4: 週 | B4: 期間の目安 | C4: フェーズ | D4: 公開する記事(例) | E4: 対象商品 | F4: 運用タイプ | G4: 担当 | H4: 広告アクション
A5: W1-2 | B5: 〜Day14 | C5: 土台 | D5: 選び方ピラー＋著者プロフィール整備／PR表記ルール確定 | E5: 全商品 | F5: ①/監修 | G5: 北野
A6: W3-4 | B6: 〜Day30 | C6: 面取り① | D6: フロントオープンPC／軽量ジップ／多機能とは | E6: PC/ジップ/多機能 | F6: ①自社・写真広告 | G6: 雪乃
A7: W5-6 | B7: 〜Day42 | C7: 信頼① | D7: ボーケン試験検証記事(アルミ)／PR TIMES配信 | E7: クラシック/多機能アルミ | F7: ②/③ | G7: 西岡・北野 | H7: 写真広告バナー入稿
A8: W7-8 | B8: 〜Day56 | C8: 面取り② | D8: 機内持ち込み対応表／留学容量ガイド | E8: PC/多機能/留学 | F8: ①自社・写真広告 | G8: 雪乃 | H8: Google写真広告 開始
A9: W9-10 | B9: 〜Day70 | C9: 比較・収益 | D9: 多機能おすすめ比較／出張比較(アフィリ) | E9: 多機能/PC | F9: ②第三者・アフィリ | G9: 西岡 | H9: アフィリ提携・計測開始
A10: W11-12 | B10: 〜Day84 | C10: 拡張・話題 | D10: ジッパーvsフレーム／新色・留学特集PR | E10: ジップ/留学 | F10: ②/③ | G10: 西岡・北野 | H10: P-MAX 拡張
A11: W13〜 | B11: Day85〜 | C11: 改善 | D11: GA4/Search Consoleで勝ち記事をリライト→上位化 | E11: 全商品 | F11: 全タイプ | G11: 全員 | H11: ROAS見て予算再配分

Sheet ⑤ AI検索対策(LLMO)
A1: AI検索対策(LLMO/AEO)｜ChatGPT等に『リベティ』を拾わせる
A2: 生成AIは「引用しやすい一次情報・明快な構造・第三者言及」を好む。SEOと両輪で仕込む。
A5: Q&A・定義文で書く | B5: AIは明快な定義・箇条書きをそのまま引用しやすい | C5: 各記事にFAQと『◯◯とは』の一文要約を必ず入れる | D5: 全記事 | E5: 雪乃 | F5: 高
A6: 構造化データ(Schema) | B6: AI/検索がエンティティを正確に認識 | C6: Product/FAQ/Review/BreadcrumbのJSON-LDを実装 | D6: 全記事 | E6: 西岡 | F6: 高
A7: 一次情報(独自データ) | B7: AIは「出典になれる」独自データを引用しやすい | C7: ボーケン試験結果・自社調査を数値で公開 | D7: 検証記事 | E7: 西岡 | F7: 高
A8: 第三者言及を増やす | B8: AIは複数ソースで言及される対象を推奨しやすい | C8: PR TIMES配信→メディア転載→被リンク/言及を蓄積 | D8: ③PR TIMES | E8: 北野 | F8: 高
A9: エンティティ一貫性 | B9: 「リベティ=多機能スーツケース」の関連を学習させる | C9: 社名/商品名/特徴の表記を全媒体で統一 | D9: 全媒体 | E9: 北野 | F9: 中
A10: 比較表を載せる | B10: AIは表を要約・引用しやすい | C10: 主要スペックの比較表を各カテゴリに設置 | D10: 比較記事 | E10: 西岡 | F10: 中
A11: 著者情報(E-E-A-T) | B11: 誰が書いたかが信頼源として評価される | C11: 著者プロフィール・監修者・更新日を明記 | D11: 全記事 | E11: 北野 | F11: 中
A12: llms.txt / 明快なsite構造 | B12: AIクローラが要点を取得しやすい | C12: 主要ページ要約のllms.txt設置・内部リンク整理 | D12: サイト全体 | E12: 西岡 | F12: 低
